{"v":"5.6.6","fr":24,"ip":0,"op":336,"w":2000,"h":2000,"nm":"NVc 2","ddd":0,"assets":[],"layers":[{"ddd":0,"ind":1,"ty":4,"nm":"thoughts Outlines","sr":1,"ks":{"o":{"a":0,"k":100,"ix":11},"r":{"a":0,"k":0,"ix":10},"p":{"a":0,"k":[1591.748,485.77,0],"ix":2},"a":{"a":0,"k":[355.378,237.92,0],"ix":1},"s":{"a":0,"k":[100,100,100],"ix":6}},"ao":0,"shapes":[{"ty":"gr","it":[{"ind":0,"ty":"sh","ix":1,"ks":{"a":0,"k":{"i":[[38.171,-9.233],[5.526,-3.088],[0.556,2.301],[53.751,-13.002],[11.313,-9.309],[42.933,-10.385],[-11.682,-48.298],[-1.263,-3.377],[16.433,-3.974],[-10.74,-44.403],[-38.199,1.055],[-59.623,14.422],[-6.255,2.79],[-16.253,3.932],[-10.213,9.826],[-21.524,5.207],[10.74,44.402],[0.362,1.241],[-15.414,3.728],[9.233,38.171]],"o":[[-6.454,1.561],[-0.389,-2.299],[-13.002,-53.751],[-15.193,3.675],[-17.271,-39.005],[-48.298,11.682],[0.87,3.592],[-14.778,-5.382],[-44.403,10.741],[9.346,38.634],[16.672,58.457],[6.895,-1.668],[14.653,5.233],[14.768,-3.572],[17.762,10.284],[44.404,-10.74],[-0.308,-1.271],[13.558,5.749],[38.17,-9.233],[-9.232,-38.17]],"v":[[185.462,-76.847],[167.491,-69.742],[166.103,-76.643],[45.236,-150.426],[5.195,-130.478],[-98.131,-181.441],[-164.429,-72.837],[-161.162,-62.415],[-208.836,-65.082],[-269.788,34.764],[-187.185,97.991],[-50.896,177.404],[-31.17,170.655],[16.011,173.164],[53.806,152.38],[114.654,161.248],[175.606,61.403],[174.505,57.685],[218.898,61.382],[271.295,-24.451]],"c":true},"ix":2},"nm":"Path 1","mn":"ADBE Vector Shape - Group","hd":false},{"ty":"st","c":{"a":0,"k":[0.793050309723,0.922270711263,0.946181832108,1],"ix":3},"o":{"a":0,"k":100,"ix":4},"w":{"a":0,"k":5,"ix":5},"lc":1,"lj":1,"ml":10,"bm":0,"nm":"Stroke 1","mn":"ADBE Vector Graphic - Stroke","hd":false},{"ty":"fl","c":{"a":0,"k":[0.999999940162,0.999999940162,1,1],"ix":4},"o":{"a":0,"k":100,"ix":5},"r":1,"bm":0,"nm":"Fill 1","mn":"ADBE Vector Graphic - Fill","hd":false},{"ty":"tr","p":{"a":0,"k":[418.733,203.321],"ix":2},"a":{"a":0,"k":[0,0],"ix":1},"s":{"a":0,"k":[100,100],"ix":3},"r":{"a":0,"k":0,"ix":6},"o":{"a":1,"k":[{"i":{"x":[0.833],"y":[0.833]},"o":{"x":[0.167],"y":[0.167]},"t":68,"s":[0]},{"i":{"x":[0.833],"y":[0.833]},"o":{"x":[0.167],"y":[0.167]},"t":82,"s":[100]},{"i":{"x":[0.833],"y":[0.833]},"o":{"x":[0.167],"y":[0.167]},"t":320,"s":[100]},{"t":333,"s":[0]}],"ix":7},"sk":{"a":0,"k":0,"ix":4},"sa":{"a":0,"k":0,"ix":5},"nm":"Transform"}],"nm":"Group 1","np":3,"cix":2,"bm":0,"ix":1,"mn":"ADBE Vector Group","hd":false},{"ty":"gr","it":[{"ind":0,"ty":"sh","ix":1,"ks":{"a":0,"k":{"i":[[0,-30.759],[30.758,0],[0,30.758],[-30.758,0]],"o":[[0,30.758],[-30.758,0],[0,-30.759],[30.758,0]],"v":[[55.693,0],[0,55.693],[-55.693,0],[0,-55.693]],"c":true},"ix":2},"nm":"Path 1","mn":"ADBE Vector Shape - Group","hd":false},{"ty":"st","c":{"a":0,"k":[0.793050309723,0.922270711263,0.946181832108,1],"ix":3},"o":{"a":0,"k":100,"ix":4},"w":{"a":0,"k":5,"ix":5},"lc":1,"lj":1,"ml":10,"bm":0,"nm":"Stroke 1","mn":"ADBE Vector Graphic - Stroke","hd":false},{"ty":"fl","c":{"a":0,"k":[0.999999940162,0.999999940162,1,1],"ix":4},"o":{"a":0,"k":100,"ix":5},"r":1,"bm":0,"nm":"Fill 1","mn":"ADBE Vector Graphic - Fill","hd":false},{"ty":"tr","p":{"a":0,"k":[135.1,365.494],"ix":2},"a":{"a":0,"k":[0,0],"ix":1},"s":{"a":0,"k":[100,100],"ix":3},"r":{"a":0,"k":0,"ix":6},"o":{"a":1,"k":[{"i":{"x":[0.833],"y":[0.833]},"o":{"x":[0.167],"y":[0.167]},"t":64,"s":[0]},{"i":{"x":[0.833],"y":[0.833]},"o":{"x":[0.167],"y":[0.167]},"t":78,"s":[100]},{"i":{"x":[0.833],"y":[0.833]},"o":{"x":[0.167],"y":[0.167]},"t":316,"s":[100]},{"t":329,"s":[0]}],"ix":7},"sk":{"a":0,"k":0,"ix":4},"sa":{"a":0,"k":0,"ix":5},"nm":"Transform"}],"nm":"Group 2","np":3,"cix":2,"bm":0,"ix":2,"mn":"ADBE Vector Group","hd":false},{"ty":"gr","it":[{"ind":0,"ty":"sh","ix":1,"ks":{"a":0,"k":{"i":[[0,-17.088],[17.087,0],[0,17.088],[-17.088,0]],"o":[[0,17.088],[-17.088,0],[0,-17.088],[17.087,0]],"v":[[30.941,0],[0,30.94],[-30.941,0],[0,-30.94]],"c":true},"ix":2},"nm":"Path 1","mn":"ADBE Vector Shape - Group","hd":false},{"ty":"st","c":{"a":0,"k":[0.793050309723,0.922270711263,0.946181832108,1],"ix":3},"o":{"a":0,"k":100,"ix":4},"w":{"a":0,"k":5,"ix":5},"lc":1,"lj":1,"ml":10,"bm":0,"nm":"Stroke 1","mn":"ADBE Vector Graphic - Stroke","hd":false},{"ty":"fl","c":{"a":0,"k":[0.999999940162,0.999999940162,1,1],"ix":4},"o":{"a":0,"k":100,"ix":5},"r":1,"bm":0,"nm":"Fill 1","mn":"ADBE Vector Graphic - Fill","hd":false},{"ty":"tr","p":{"a":0,"k":[48.466,427.374],"ix":2},"a":{"a":0,"k":[0,0],"ix":1},"s":{"a":0,"k":[100,100],"ix":3},"r":{"a":0,"k":0,"ix":6},"o":{"a":1,"k":[{"i":{"x":[0.833],"y":[0.833]},"o":{"x":[0.167],"y":[0.167]},"t":61,"s":[0]},{"i":{"x":[0.833],"y":[0.833]},"o":{"x":[0.167],"y":[0.167]},"t":75,"s":[100]},{"i":{"x":[0.833],"y":[0.833]},"o":{"x":[0.167],"y":[0.167]},"t":313,"s":[100]},{"t":326,"s":[0]}],"ix":7},"sk":{"a":0,"k":0,"ix":4},"sa":{"a":0,"k":0,"ix":5},"nm":"Transform"}],"nm":"Group 3","np":3,"cix":2,"bm":0,"ix":3,"mn":"ADBE Vector Group","hd":false}],"ip":0,"op":514,"st":0,"bm":0},{"ddd":0,"ind":2,"ty":4,"nm":"words Outlines","sr":1,"ks":{"o":{"a":1,"k":[{"i":{"x":[0.833],"y":[0.833]},"o":{"x":[0.167],"y":[0.167]},"t":119,"s":[0]},{"i":{"x":[0.833],"y":[0.833]},"o":{"x":[0.167],"y":[0.167]},"t":137,"s":[100]},{"i":{"x":[0.833],"y":[0.833]},"o":{"x":[0.167],"y":[0.167]},"t":305,"s":[100]},{"t":320,"s":[0]}],"ix":11},"r":{"a":0,"k":0,"ix":10},"p":{"a":0,"k":[384.902,782.498,0],"ix":2},"a":{"a":0,"k":[305.982,190.191,0],"ix":1},"s":{"a":0,"k":[100,100,100],"ix":6}},"ao":0,"shapes":[{"ty":"gr","it":[{"ind":0,"ty":"sh","ix":1,"ks":{"a":0,"k":{"i":[[0,49.789],[161.978,0],[0,-92.053],[-161.977,0],[-40.703,12.154],[-18.706,5.612],[0,0]],"o":[[0,-92.053],[-161.977,0],[0,92.053],[49.172,0],[15.972,19.029],[0,0],[60.903,-30.542]],"v":[[293.286,-10.819],[-0.001,-177.496],[-293.287,-10.819],[-0.001,155.857],[136.184,136.792],[193.921,171.884],[193.921,114.172]],"c":true},"ix":2},"nm":"Path 1","mn":"ADBE Vector Shape - Group","hd":false},{"ty":"st","c":{"a":0,"k":[0.793050309723,0.922270711263,0.946181832108,1],"ix":3},"o":{"a":0,"k":100,"ix":4},"w":{"a":0,"k":5.078,"ix":5},"lc":1,"lj":1,"ml":10,"bm":0,"nm":"Stroke 1","mn":"ADBE Vector Graphic - Stroke","hd":false},{"ty":"fl","c":{"a":0,"k":[0.999999940162,0.999999940162,1,1],"ix":4},"o":{"a":0,"k":100,"ix":5},"r":1,"bm":0,"nm":"Fill 1","mn":"ADBE Vector Graphic - Fill","hd":false},{"ty":"tr","p":{"a":0,"k":[305.982,190.191],"ix":2},"a":{"a":0,"k":[0,0],"ix":1},"s":{"a":0,"k":[100,100],"ix":3},"r":{"a":0,"k":0,"ix":6},"o":{"a":0,"k":100,"ix":7},"sk":{"a":0,"k":0,"ix":4},"sa":{"a":0,"k":0,"ix":5},"nm":"Transform"}],"nm":"Group 1","np":3,"cix":2,"bm":0,"ix":1,"mn":"ADBE Vector Group","hd":false}],"ip":0,"op":514,"st":0,"bm":0},{"ddd":0,"ind":4,"ty":4,"nm":"frangetta Outlines","parent":10,"sr":1,"ks":{"o":{"a":0,"k":100,"ix":11},"r":{"a":1,"k":[{"i":{"x":[0.667],"y":[1]},"o":{"x":[0.333],"y":[0]},"t":5,"s":[0]},{"i":{"x":[0.667],"y":[1]},"o":{"x":[0.333],"y":[0]},"t":18,"s":[-6]},{"i":{"x":[0.667],"y":[1]},"o":{"x":[0.333],"y":[0]},"t":35,"s":[0]},{"i":{"x":[0.667],"y":[1]},"o":{"x":[0.333],"y":[0]},"t":193,"s":[0]},{"i":{"x":[0.667],"y":[1]},"o":{"x":[0.333],"y":[0]},"t":220,"s":[6]},{"i":{"x":[0.667],"y":[1]},"o":{"x":[0.333],"y":[0]},"t":286,"s":[-6]},{"t":326,"s":[0]}],"ix":10},"p":{"a":0,"k":[254.422,115.759,0],"ix":2},"a":{"a":0,"k":[271.924,243.321,0],"ix":1},"s":{"a":0,"k":[100,100,100],"ix":6}},"ao":0,"shapes":[{"ty":"gr","it":[{"ind":0,"ty":"sh","ix":1,"ks":{"a":0,"k":{"i":[[0,0],[-51.794,20.091],[-6.413,-0.351],[-9.22,-0.502],[-16.273,-0.679],[0,0],[0,0],[14.027,-14.027],[0,0],[0,0],[26.302,42.083],[0,0],[194.634,-8.767],[58.094,-114.251]],"o":[[0,0],[-8.767,-19.288],[-8.768,36.823],[57.9,3.149],[22.795,-45.59],[0,0],[0,0],[-14.027,14.027],[0,0],[0,0],[-26.302,-42.083],[0,0],[-194.634,8.767],[-15.431,30.348]],"v":[[-254.306,-2.328],[-63.236,-39.67],[-45.702,-92.274],[-38.806,-35.752],[87.561,-29.149],[133.151,-67.725],[136.658,-39.67],[107.021,229.044],[188.728,229.044],[187.348,-1.573],[245.372,-95.781],[185.755,-118.576],[15.669,-234.304],[-256.243,-128.197]],"c":true},"ix":2},"nm":"Path 1","mn":"ADBE Vector Shape - Group","hd":false},{"ty":"fl","c":{"a":0,"k":[0.793050309723,0.922270711263,0.946181832108,1],"ix":4},"o":{"a":0,"k":100,"ix":5},"r":1,"bm":0,"nm":"Fill 1","mn":"ADBE Vector Graphic - Fill","hd":false},{"ty":"tr","p":{"a":0,"k":[271.924,243.321],"ix":2},"a":{"a":0,"k":[0,0],"ix":1},"s":{"a":0,"k":[100,100],"ix":3},"r":{"a":0,"k":0,"ix":6},"o":{"a":0,"k":100,"ix":7},"sk":{"a":0,"k":0,"ix":4},"sa":{"a":0,"k":0,"ix":5},"nm":"Transform"}],"nm":"Group 1","np":2,"cix":2,"bm":0,"ix":1,"mn":"ADBE Vector Group","hd":false}],"ip":-1,"op":519,"st":5,"bm":0},{"ddd":0,"ind":5,"ty":4,"nm":"eye Outlines 3","parent":10,"sr":1,"ks":{"o":{"a":0,"k":100,"ix":11},"r":{"a":0,"k":0,"ix":10},"p":{"a":0,"k":[189.499,180.159,0],"ix":2},"a":{"a":0,"k":[166.386,41.702,0],"ix":1},"s":{"a":0,"k":[100,100,100],"ix":6}},"ao":0,"shapes":[{"ty":"gr","it":[{"ind":0,"ty":"sh","ix":1,"ks":{"a":1,"k":[{"i":{"x":0.667,"y":1},"o":{"x":0.333,"y":0},"t":0,"s":[{"i":[[0,0],[42.04,-1.819],[-1.479,-3.534],[-34.476,-2.541]],"o":[[0,0],[-18.768,0.813],[1.834,4.382],[36.092,2.66]],"v":[[50.232,10.228],[-8.192,-12.028],[-30.804,-4.856],[0.914,-14.436]],"c":true}]},{"i":{"x":0.667,"y":1},"o":{"x":0.333,"y":0},"t":7,"s":[{"i":[[0,0],[42.04,-1.819],[-2.56,-3.878],[-9.524,-3.839]],"o":[[0,0],[-20.073,0.869],[2.801,4.244],[11.866,4.784]],"v":[[50.232,10.228],[-11.192,-15.028],[-30.399,-4.109],[-6.586,9.064]],"c":true}]},{"i":{"x":0.667,"y":1},"o":{"x":0.333,"y":0},"t":14,"s":[{"i":[[0,0],[42.04,-1.819],[-1.479,-3.534],[-34.476,-2.541]],"o":[[0,0],[-18.768,0.813],[1.834,4.382],[36.092,2.66]],"v":[[50.232,10.228],[-8.192,-12.028],[-30.804,-4.856],[0.914,-14.436]],"c":true}]},{"i":{"x":0.667,"y":1},"o":{"x":0.333,"y":0},"t":113,"s":[{"i":[[0,0],[42.04,-1.819],[-1.479,-3.534],[-34.476,-2.541]],"o":[[0,0],[-18.768,0.813],[1.834,4.382],[36.092,2.66]],"v":[[50.232,10.228],[-8.192,-12.028],[-30.804,-4.856],[0.914,-14.436]],"c":true}]},{"i":{"x":0.667,"y":1},"o":{"x":0.333,"y":0},"t":120,"s":[{"i":[[0,0],[42.04,-1.819],[-2.56,-3.878],[-9.524,-3.839]],"o":[[0,0],[-20.073,0.869],[2.801,4.244],[11.866,4.784]],"v":[[50.232,10.228],[-11.192,-15.028],[-30.399,-4.109],[-6.586,9.064]],"c":true}]},{"i":{"x":0.667,"y":1},"o":{"x":0.333,"y":0},"t":127,"s":[{"i":[[0,0],[42.04,-1.819],[-1.479,-3.534],[-34.476,-2.541]],"o":[[0,0],[-18.768,0.813],[1.834,4.382],[36.092,2.66]],"v":[[50.232,10.228],[-8.192,-12.028],[-30.804,-4.856],[0.914,-14.436]],"c":true}]},{"i":{"x":0.667,"y":1},"o":{"x":0.333,"y":0},"t":173,"s":[{"i":[[0,0],[42.04,-1.819],[-1.479,-3.534],[-34.476,-2.541]],"o":[[0,0],[-18.768,0.813],[1.834,4.382],[36.092,2.66]],"v":[[50.232,10.228],[-8.192,-12.028],[-30.804,-4.856],[0.914,-14.436]],"c":true}]},{"i":{"x":0.667,"y":1},"o":{"x":0.333,"y":0},"t":180,"s":[{"i":[[0,0],[42.04,-1.819],[-2.56,-3.878],[-9.524,-3.839]],"o":[[0,0],[-20.073,0.869],[2.801,4.244],[11.866,4.784]],"v":[[50.232,10.228],[-11.192,-15.028],[-30.399,-4.109],[-6.586,9.064]],"c":true}]},{"i":{"x":0.667,"y":1},"o":{"x":0.167,"y":0},"t":187,"s":[{"i":[[0,0],[42.04,-1.819],[-1.479,-3.534],[-34.476,-2.541]],"o":[[0,0],[-18.768,0.813],[1.834,4.382],[36.092,2.66]],"v":[[50.232,10.228],[-8.192,-12.028],[-30.804,-4.856],[0.914,-14.436]],"c":true}]},{"i":{"x":0.667,"y":1},"o":{"x":0.333,"y":0},"t":281,"s":[{"i":[[0,0],[42.04,-1.819],[-1.479,-3.534],[-34.476,-2.541]],"o":[[0,0],[-18.768,0.813],[1.834,4.382],[36.092,2.66]],"v":[[50.232,10.228],[-8.192,-12.028],[-30.804,-4.856],[0.914,-14.436]],"c":true}]},{"i":{"x":0.667,"y":1},"o":{"x":0.333,"y":0},"t":288,"s":[{"i":[[0,0],[42.04,-1.819],[-2.56,-3.878],[-9.524,-3.839]],"o":[[0,0],[-20.073,0.869],[2.801,4.244],[11.866,4.784]],"v":[[50.232,10.228],[-11.192,-15.028],[-30.399,-4.109],[-6.586,9.064]],"c":true}]},{"t":295,"s":[{"i":[[0,0],[42.04,-1.819],[-1.479,-3.534],[-34.476,-2.541]],"o":[[0,0],[-18.768,0.813],[1.834,4.382],[36.092,2.66]],"v":[[50.232,10.228],[-8.192,-12.028],[-30.804,-4.856],[0.914,-14.436]],"c":true}]}],"ix":2},"nm":"Path 1","mn":"ADBE Vector Shape - Group","hd":false},{"ty":"fl","c":{"a":0,"k":[0.262745098039,0.078431372549,0.03137254902,1],"ix":4},"o":{"a":0,"k":100,"ix":5},"r":1,"bm":0,"nm":"Fill 1","mn":"ADBE Vector Graphic - Fill","hd":false},{"ty":"tr","p":{"a":0,"k":[50.482,69.306],"ix":2},"a":{"a":0,"k":[0,0],"ix":1},"s":{"a":0,"k":[100,100],"ix":3},"r":{"a":0,"k":0,"ix":6},"o":{"a":0,"k":100,"ix":7},"sk":{"a":0,"k":0,"ix":4},"sa":{"a":0,"k":0,"ix":5},"nm":"Transform"}],"nm":"Group 1","np":2,"cix":2,"bm":0,"ix":1,"mn":"ADBE Vector Group","hd":false},{"ty":"gr","it":[{"ind":0,"ty":"sh","ix":1,"ks":{"a":1,"k":[{"i":{"x":0.667,"y":1},"o":{"x":0.333,"y":0},"t":0,"s":[{"i":[[7.28,-13.989],[-33.353,7.463],[0,0],[23.537,-5.565]],"o":[[0,0],[40.172,-8.988],[0,0],[-42.516,10.052]],"v":[[-51.369,18.581],[-8.261,-15.92],[51.369,-16.731],[11.427,-24.461]],"c":true}]},{"i":{"x":0.667,"y":1},"o":{"x":0.333,"y":0},"t":7,"s":[{"i":[[9.28,2.511],[-39.133,3.671],[0,0],[33.383,-10.324]],"o":[[0,0],[39.133,-3.673],[0,0],[-19.926,6.162]],"v":[[-51.369,18.581],[9.239,-23.92],[51.369,-16.731],[4.028,13.916]],"c":true}]},{"i":{"x":0.667,"y":1},"o":{"x":0.333,"y":0},"t":14,"s":[{"i":[[7.28,-13.989],[-33.353,7.463],[0,0],[23.537,-5.565]],"o":[[0,0],[40.172,-8.988],[0,0],[-42.516,10.052]],"v":[[-51.369,18.581],[-8.261,-15.92],[51.369,-16.731],[11.427,-24.461]],"c":true}]},{"i":{"x":0.667,"y":1},"o":{"x":0.333,"y":0},"t":113,"s":[{"i":[[7.28,-13.989],[-33.353,7.463],[0,0],[23.537,-5.565]],"o":[[0,0],[40.172,-8.988],[0,0],[-42.516,10.052]],"v":[[-51.369,18.581],[-8.261,-15.92],[51.369,-16.731],[11.427,-24.461]],"c":true}]},{"i":{"x":0.667,"y":1},"o":{"x":0.333,"y":0},"t":120,"s":[{"i":[[9.28,2.511],[-39.133,3.671],[0,0],[33.383,-10.324]],"o":[[0,0],[39.133,-3.673],[0,0],[-19.926,6.162]],"v":[[-51.369,18.581],[9.239,-23.92],[51.369,-16.731],[4.028,13.916]],"c":true}]},{"i":{"x":0.667,"y":1},"o":{"x":0.333,"y":0},"t":127,"s":[{"i":[[7.28,-13.989],[-33.353,7.463],[0,0],[23.537,-5.565]],"o":[[0,0],[40.172,-8.988],[0,0],[-42.516,10.052]],"v":[[-51.369,18.581],[-8.261,-15.92],[51.369,-16.731],[11.427,-24.461]],"c":true}]},{"i":{"x":0.667,"y":1},"o":{"x":0.333,"y":0},"t":173,"s":[{"i":[[7.28,-13.989],[-33.353,7.463],[0,0],[23.537,-5.565]],"o":[[0,0],[40.172,-8.988],[0,0],[-42.516,10.052]],"v":[[-51.369,18.581],[-8.261,-15.92],[51.369,-16.731],[11.427,-24.461]],"c":true}]},{"i":{"x":0.667,"y":1},"o":{"x":0.333,"y":0},"t":180,"s":[{"i":[[9.28,2.511],[-39.133,3.671],[0,0],[33.383,-10.324]],"o":[[0,0],[39.133,-3.673],[0,0],[-19.926,6.162]],"v":[[-51.369,18.581],[9.239,-23.92],[51.369,-16.731],[4.028,13.916]],"c":true}]},{"i":{"x":0.667,"y":1},"o":{"x":0.167,"y":0},"t":187,"s":[{"i":[[7.28,-13.989],[-33.353,7.463],[0,0],[23.537,-5.565]],"o":[[0,0],[40.172,-8.988],[0,0],[-42.516,10.052]],"v":[[-51.369,18.581],[-8.261,-15.92],[51.369,-16.731],[11.427,-24.461]],"c":true}]},{"i":{"x":0.667,"y":1},"o":{"x":0.333,"y":0},"t":281,"s":[{"i":[[7.28,-13.989],[-33.353,7.463],[0,0],[23.537,-5.565]],"o":[[0,0],[40.172,-8.988],[0,0],[-42.516,10.052]],"v":[[-51.369,18.581],[-8.261,-15.92],[51.369,-16.731],[11.427,-24.461]],"c":true}]},{"i":{"x":0.667,"y":1},"o":{"x":0.333,"y":0},"t":288,"s":[{"i":[[9.28,2.511],[-39.133,3.671],[0,0],[33.383,-10.324]],"o":[[0,0],[39.133,-3.673],[0,0],[-19.926,6.162]],"v":[[-51.369,18.581],[9.239,-23.92],[51.369,-16.731],[4.028,13.916]],"c":true}]},{"t":295,"s":[{"i":[[7.28,-13.989],[-33.353,7.463],[0,0],[23.537,-5.565]],"o":[[0,0],[40.172,-8.988],[0,0],[-42.516,10.052]],"v":[[-51.369,18.581],[-8.261,-15.92],[51.369,-16.731],[11.427,-24.461]],"c":true}]}],"ix":2},"nm":"Path 1","mn":"ADBE Vector Shape - Group","hd":false},{"ty":"fl","c":{"a":0,"k":[0.262745098039,0.078431372549,0.03137254902,1],"ix":4},"o":{"a":0,"k":100,"ix":5},"r":1,"bm":0,"nm":"Fill 1","mn":"ADBE Vector Graphic - Fill","hd":false},{"ty":"tr","p":{"a":0,"k":[266.078,41.938],"ix":2},"a":{"a":0,"k":[0,0],"ix":1},"s":{"a":0,"k":[100,100],"ix":3},"r":{"a":0,"k":0,"ix":6},"o":{"a":0,"k":100,"ix":7},"sk":{"a":0,"k":0,"ix":4},"sa":{"a":0,"k":0,"ix":5},"nm":"Transform"}],"nm":"Group 2","np":2,"cix":2,"bm":0,"ix":2,"mn":"ADBE Vector Group","hd":false}],"ip":0,"op":514,"st":0,"bm":0},{"ddd":0,"ind":7,"ty":4,"nm":"eye Outlines","parent":10,"sr":1,"ks":{"o":{"a":0,"k":100,"ix":11},"r":{"a":0,"k":0,"ix":10},"p":{"a":0,"k":[189.499,180.159,0],"ix":2},"a":{"a":0,"k":[166.386,41.702,0],"ix":1},"s":{"a":0,"k":[100,100,100],"ix":6}},"ao":0,"shapes":[{"ty":"gr","it":[{"ind":0,"ty":"sh","ix":1,"ks":{"a":0,"k":{"i":[[0,0],[36.163,-1.063],[0,0],[0,0],[-31.486,-2.863]],"o":[[0,0],[-36.163,1.063],[0,0],[0,0],[27.021,2.457]],"v":[[50.202,16.469],[-14.039,-15.406],[-37.682,-8.848],[-36.341,-0.574],[2.733,-4.933]],"c":true},"ix":2},"nm":"Path 1","mn":"ADBE Vector Shape - Group","hd":false},{"ty":"fl","c":{"a":0,"k":[0.261918550379,0.078588964425,0.032551380232,1],"ix":4},"o":{"a":0,"k":100,"ix":5},"r":1,"bm":0,"nm":"Fill 1","mn":"ADBE Vector Graphic - Fill","hd":false},{"ty":"tr","p":{"a":0,"k":[53.604,63.797],"ix":2},"a":{"a":0,"k":[0,0],"ix":1},"s":{"a":0,"k":[100,100],"ix":3},"r":{"a":0,"k":0,"ix":6},"o":{"a":0,"k":100,"ix":7},"sk":{"a":0,"k":0,"ix":4},"sa":{"a":0,"k":0,"ix":5},"nm":"Transform"}],"nm":"Group 3","np":2,"cix":2,"bm":0,"ix":3,"mn":"ADBE Vector Group","hd":false},{"ty":"gr","it":[{"ind":0,"ty":"sh","ix":1,"ks":{"a":0,"k":{"i":[[0,0],[-39.354,11.7],[0,0],[0,0],[30.299,-11.513]],"o":[[0,0],[39.355,-11.7],[0,0],[0,0],[-43.486,16.525]],"v":[[-58.907,30.134],[-1.828,-18.434],[58.907,-17.719],[44.635,-5.177],[-8.438,-3.733]],"c":true},"ix":2},"nm":"Path 1","mn":"ADBE Vector Shape - Group","hd":false},{"ty":"fl","c":{"a":0,"k":[0.261918550379,0.078588964425,0.032551380232,1],"ix":4},"o":{"a":0,"k":100,"ix":5},"r":1,"bm":0,"nm":"Fill 1","mn":"ADBE Vector Graphic - Fill","hd":false},{"ty":"tr","p":{"a":0,"k":[273.615,30.385],"ix":2},"a":{"a":0,"k":[0,0],"ix":1},"s":{"a":0,"k":[100,100],"ix":3},"r":{"a":0,"k":0,"ix":6},"o":{"a":0,"k":100,"ix":7},"sk":{"a":0,"k":0,"ix":4},"sa":{"a":0,"k":0,"ix":5},"nm":"Transform"}],"nm":"Group 4","np":2,"cix":2,"bm":0,"ix":4,"mn":"ADBE Vector Group","hd":false}],"ip":0,"op":514,"st":0,"bm":0},{"ddd":0,"ind":8,"ty":4,"nm":"lips Outlines","parent":10,"sr":1,"ks":{"o":{"a":0,"k":100,"ix":11},"r":{"a":0,"k":0,"ix":10},"p":{"a":0,"k":[207.65,326.88,0],"ix":2},"a":{"a":0,"k":[41.034,26.745,0],"ix":1},"s":{"a":0,"k":[100,100,100],"ix":6}},"ao":0,"shapes":[{"ty":"gr","it":[{"ind":0,"ty":"sh","ix":1,"ks":{"a":1,"k":[{"i":{"x":0.667,"y":1},"o":{"x":0.333,"y":0},"t":174,"s":[{"i":[[0,0],[-9.164,-3.556],[-4.538,10.011]],"o":[[0,0],[22.167,8.599],[-20.151,5.588]],"v":[[-26.765,-8.258],[-14.379,7.01],[26.765,-15.609]],"c":true}]},{"i":{"x":0.621,"y":1},"o":{"x":1,"y":0},"t":191,"s":[{"i":[[0,0],[-9.164,-3.556],[-4.538,10.011]],"o":[[0,0],[22.167,8.599],[-20.151,5.588]],"v":[[-26.765,-8.258],[-14.379,7.01],[26.765,-23.609]],"c":true}]},{"i":{"x":0.667,"y":1},"o":{"x":0.976,"y":0},"t":211,"s":[{"i":[[0,0],[-9.164,-3.556],[-4.538,10.011]],"o":[[0,0],[22.167,8.599],[-20.151,5.588]],"v":[[-25.765,-8.258],[0.621,-11.99],[26.765,-23.609]],"c":true}]},{"t":234,"s":[{"i":[[0,0],[-9.164,-3.556],[-4.538,10.011]],"o":[[0,0],[22.167,8.599],[-20.151,5.588]],"v":[[-26.765,-8.258],[-14.379,7.01],[26.765,-15.609]],"c":true}]}],"ix":2},"nm":"Path 1","mn":"ADBE Vector Shape - Group","hd":false},{"ty":"fl","c":{"a":0,"k":[0.082259009866,0.062031566395,0.066909408569,1],"ix":4},"o":{"a":0,"k":100,"ix":5},"r":1,"bm":0,"nm":"Fill 1","mn":"ADBE Vector Graphic - Fill","hd":false},{"ty":"tr","p":{"a":0,"k":[42.705,37.63],"ix":2},"a":{"a":0,"k":[0,0],"ix":1},"s":{"a":0,"k":[100,100],"ix":3},"r":{"a":0,"k":0,"ix":6},"o":{"a":0,"k":100,"ix":7},"sk":{"a":0,"k":0,"ix":4},"sa":{"a":0,"k":0,"ix":5},"nm":"Transform"}],"nm":"Group 1","np":2,"cix":2,"bm":0,"ix":1,"mn":"ADBE Vector Group","hd":false},{"ty":"gr","it":[{"ind":0,"ty":"sh","ix":1,"ks":{"a":1,"k":[{"i":{"x":0.833,"y":0.833},"o":{"x":0.167,"y":0.167},"t":174,"s":[{"i":[[0,0],[0,0],[-7.388,-2.866],[-7.152,-1.794]],"o":[[-36.087,22.485],[0,0],[7.39,2.866],[7.151,1.793]],"v":[[40.784,-6.005],[-40.784,12.669],[-20.296,-8.263],[-1.455,-14.686]],"c":true}]},{"i":{"x":0.833,"y":0.833},"o":{"x":0.167,"y":0.167},"t":191,"s":[{"i":[[0,0],[0,0],[-7.388,-2.866],[-7.152,-1.794]],"o":[[-45.333,21.127],[0,0],[7.39,2.866],[7.151,1.793]],"v":[[43.784,-15.005],[-40.784,12.669],[-20.296,-8.263],[-1.455,-14.686]],"c":true}]},{"t":234,"s":[{"i":[[0,0],[0,0],[-7.388,-2.866],[-7.152,-1.794]],"o":[[-36.087,22.485],[0,0],[7.39,2.866],[7.151,1.793]],"v":[[40.784,-6.005],[-40.784,12.669],[-20.296,-8.263],[-1.455,-14.686]],"c":true}]}],"ix":2},"nm":"Path 1","mn":"ADBE Vector Shape - Group","hd":false},{"ty":"fl","c":{"a":0,"k":[0.082259009866,0.062031566395,0.066909408569,1],"ix":4},"o":{"a":0,"k":100,"ix":5},"r":1,"bm":0,"nm":"Fill 1","mn":"ADBE Vector Graphic - Fill","hd":false},{"ty":"tr","p":{"a":0,"k":[41.034,16.73],"ix":2},"a":{"a":0,"k":[0,0],"ix":1},"s":{"a":0,"k":[100,100],"ix":3},"r":{"a":0,"k":0,"ix":6},"o":{"a":0,"k":100,"ix":7},"sk":{"a":0,"k":0,"ix":4},"sa":{"a":0,"k":0,"ix":5},"nm":"Transform"}],"nm":"Group 2","np":2,"cix":2,"bm":0,"ix":2,"mn":"ADBE Vector Group","hd":false}],"ip":0,"op":514,"st":0,"bm":0},{"ddd":0,"ind":9,"ty":4,"nm":"eye b Outlines","parent":10,"sr":1,"ks":{"o":{"a":0,"k":100,"ix":11},"r":{"a":0,"k":0,"ix":10},"p":{"a":0,"k":[214.341,126.853,0],"ix":2},"a":{"a":0,"k":[198.527,54.186,0],"ix":1},"s":{"a":0,"k":[100,100,100],"ix":6}},"ao":0,"shapes":[{"ty":"gr","it":[{"ind":0,"ty":"sh","ix":1,"ks":{"a":0,"k":{"i":[[0,0],[0,0]],"o":[[0,0],[0,0]],"v":[[1.653,12.92],[-1.653,-12.92]],"c":false},"ix":2},"nm":"Path 1","mn":"ADBE Vector Shape - Group","hd":false},{"ty":"st","c":{"a":0,"k":[0.261918550379,0.078588964425,0.032551380232,1],"ix":3},"o":{"a":0,"k":100,"ix":4},"w":{"a":0,"k":7.01,"ix":5},"lc":1,"lj":1,"ml":10,"bm":0,"nm":"Stroke 1","mn":"ADBE Vector Graphic - Stroke","hd":false},{"ty":"tr","p":{"a":0,"k":[99.845,73.133],"ix":2},"a":{"a":0,"k":[0,0],"ix":1},"s":{"a":0,"k":[100,100],"ix":3},"r":{"a":0,"k":0,"ix":6},"o":{"a":0,"k":100,"ix":7},"sk":{"a":0,"k":0,"ix":4},"sa":{"a":0,"k":0,"ix":5},"nm":"Transform"}],"nm":"Group 1","np":2,"cix":2,"bm":0,"ix":1,"mn":"ADBE Vector Group","hd":false},{"ty":"gr","it":[{"ind":0,"ty":"sh","ix":1,"ks":{"a":0,"k":{"i":[[0,0],[0,0]],"o":[[0,0],[0,0]],"v":[[3.23,14.584],[-3.23,-14.584]],"c":false},"ix":2},"nm":"Path 1","mn":"ADBE Vector Shape - Group","hd":false},{"ty":"st","c":{"a":0,"k":[0.261918550379,0.078588964425,0.032551380232,1],"ix":3},"o":{"a":0,"k":100,"ix":4},"w":{"a":0,"k":7.01,"ix":5},"lc":1,"lj":1,"ml":10,"bm":0,"nm":"Stroke 1","mn":"ADBE Vector Graphic - Stroke","hd":false},{"ty":"tr","p":{"a":0,"k":[88.038,68.903],"ix":2},"a":{"a":0,"k":[0,0],"ix":1},"s":{"a":0,"k":[100,100],"ix":3},"r":{"a":0,"k":0,"ix":6},"o":{"a":0,"k":100,"ix":7},"sk":{"a":0,"k":0,"ix":4},"sa":{"a":0,"k":0,"ix":5},"nm":"Transform"}],"nm":"Group 2","np":2,"cix":2,"bm":0,"ix":2,"mn":"ADBE Vector Group","hd":false},{"ty":"gr","it":[{"ind":0,"ty":"sh","ix":1,"ks":{"a":0,"k":{"i":[[0,0],[0,0]],"o":[[0,0],[0,0]],"v":[[3.444,13.731],[-3.444,-13.731]],"c":false},"ix":2},"nm":"Path 1","mn":"ADBE Vector Shape - Group","hd":false},{"ty":"st","c":{"a":0,"k":[0.261918550379,0.078588964425,0.032551380232,1],"ix":3},"o":{"a":0,"k":100,"ix":4},"w":{"a":0,"k":7.01,"ix":5},"lc":1,"lj":1,"ml":10,"bm":0,"nm":"Stroke 1","mn":"ADBE Vector Graphic - Stroke","hd":false},{"ty":"tr","p":{"a":0,"k":[188.537,62.753],"ix":2},"a":{"a":0,"k":[0,0],"ix":1},"s":{"a":0,"k":[100,100],"ix":3},"r":{"a":0,"k":0,"ix":6},"o":{"a":0,"k":100,"ix":7},"sk":{"a":0,"k":0,"ix":4},"sa":{"a":0,"k":0,"ix":5},"nm":"Transform"}],"nm":"Group 3","np":2,"cix":2,"bm":0,"ix":3,"mn":"ADBE Vector Group","hd":false},{"ty":"gr","it":[{"ind":0,"ty":"sh","ix":1,"ks":{"a":0,"k":{"i":[[0,0],[0,0]],"o":[[0,0],[0,0]],"v":[[2.459,18.378],[-2.459,-18.378]],"c":false},"ix":2},"nm":"Path 1","mn":"ADBE Vector Shape - Group","hd":false},{"ty":"st","c":{"a":0,"k":[0.261918550379,0.078588964425,0.032551380232,1],"ix":3},"o":{"a":0,"k":100,"ix":4},"w":{"a":0,"k":7.01,"ix":5},"lc":1,"lj":1,"ml":10,"bm":0,"nm":"Stroke 1","mn":"ADBE Vector Graphic - Stroke","hd":false},{"ty":"tr","p":{"a":0,"k":[198.732,56.067],"ix":2},"a":{"a":0,"k":[0,0],"ix":1},"s":{"a":0,"k":[100,100],"ix":3},"r":{"a":0,"k":0,"ix":6},"o":{"a":0,"k":100,"ix":7},"sk":{"a":0,"k":0,"ix":4},"sa":{"a":0,"k":0,"ix":5},"nm":"Transform"}],"nm":"Group 4","np":2,"cix":2,"bm":0,"ix":4,"mn":"ADBE Vector Group","hd":false},{"ty":"gr","it":[{"ind":0,"ty":"sh","ix":1,"ks":{"a":1,"k":[{"i":{"x":0.667,"y":1},"o":{"x":0.333,"y":0},"t":93,"s":[{"i":[[-12.482,-3.131],[20.04,11.41],[4.535,-12.794],[-0.787,15.572]],"o":[[12.482,3.13],[-20.039,-11.41],[-4.535,12.793],[0.786,-15.571]],"v":[[32.476,14.575],[17.862,-24.829],[-40.422,-17.133],[-34.87,20.667]],"c":true}]},{"i":{"x":0.667,"y":1},"o":{"x":0.333,"y":0},"t":130,"s":[{"i":[[-12.482,-3.131],[20.04,11.41],[4.535,-12.794],[-0.787,15.572]],"o":[[12.482,3.13],[-20.039,-11.41],[-4.535,12.793],[0.786,-15.571]],"v":[[32.476,14.575],[17.862,-24.829],[-42.422,-41.133],[-36.87,-4.333]],"c":true}]},{"t":165,"s":[{"i":[[-12.482,-3.131],[20.04,11.41],[4.535,-12.794],[-0.787,15.572]],"o":[[12.482,3.13],[-20.039,-11.41],[-4.535,12.793],[0.786,-15.571]],"v":[[32.476,14.575],[17.862,-24.829],[-40.422,-17.133],[-34.87,20.667]],"c":true}]}],"ix":2},"nm":"Path 1","mn":"ADBE Vector Shape - Group","hd":false},{"ty":"fl","c":{"a":0,"k":[0.261918550379,0.078588964425,0.032551380232,1],"ix":4},"o":{"a":0,"k":100,"ix":5},"r":1,"bm":0,"nm":"Fill 1","mn":"ADBE Vector Graphic - Fill","hd":false},{"ty":"tr","p":{"a":0,"k":[45.207,71.883],"ix":2},"a":{"a":0,"k":[0,0],"ix":1},"s":{"a":0,"k":[100,100],"ix":3},"r":{"a":0,"k":0,"ix":6},"o":{"a":0,"k":100,"ix":7},"sk":{"a":0,"k":0,"ix":4},"sa":{"a":0,"k":0,"ix":5},"nm":"Transform"}],"nm":"Group 5","np":2,"cix":2,"bm":0,"ix":5,"mn":"ADBE Vector Group","hd":false},{"ty":"gr","it":[{"ind":0,"ty":"sh","ix":1,"ks":{"a":1,"k":[{"i":{"x":0.667,"y":1},"o":{"x":0.333,"y":0},"t":64,"s":[{"i":[[-21.091,-53.018],[-42.445,-5.338],[0,0],[48.646,8.857],[0,0]],"o":[[0,0],[42.444,5.338],[0,0],[-56.968,-10.373],[0,0]],"v":[[-83.296,38.635],[49.238,11.704],[104.387,18.446],[42.466,-28.262],[-55.878,-22.996]],"c":true}]},{"i":{"x":0.667,"y":1},"o":{"x":0.333,"y":0},"t":94,"s":[{"i":[[-21.091,-53.018],[-42.445,-5.338],[0,0],[48.646,8.857],[0,0]],"o":[[0,0],[42.444,5.338],[0,0],[-56.968,-10.373],[0,0]],"v":[[-83.296,38.635],[43.238,-20.296],[104.387,-13.554],[46.466,-46.262],[-55.878,-22.996]],"c":true}]},{"t":130,"s":[{"i":[[-21.091,-53.018],[-42.445,-5.338],[0,0],[48.646,8.857],[0,0]],"o":[[0,0],[42.444,5.338],[0,0],[-56.968,-10.373],[0,0]],"v":[[-83.296,38.635],[49.238,11.704],[104.387,18.446],[42.466,-28.262],[-55.878,-22.996]],"c":true}]}],"ix":2},"nm":"Path 1","mn":"ADBE Vector Shape - Group","hd":false},{"ty":"fl","c":{"a":0,"k":[0.261918550379,0.078588964425,0.032551380232,1],"ix":4},"o":{"a":0,"k":100,"ix":5},"r":1,"bm":0,"nm":"Fill 1","mn":"ADBE Vector Graphic - Fill","hd":false},{"ty":"tr","p":{"a":0,"k":[292.416,38.885],"ix":2},"a":{"a":0,"k":[0,0],"ix":1},"s":{"a":0,"k":[100,100],"ix":3},"r":{"a":0,"k":0,"ix":6},"o":{"a":0,"k":100,"ix":7},"sk":{"a":0,"k":0,"ix":4},"sa":{"a":0,"k":0,"ix":5},"nm":"Transform"}],"nm":"Group 6","np":2,"cix":2,"bm":0,"ix":6,"mn":"ADBE Vector Group","hd":false}],"ip":0,"op":514,"st":0,"bm":0},{"ddd":0,"ind":10,"ty":4,"nm":"faccia Outlines","sr":1,"ks":{"o":{"a":0,"k":100,"ix":11},"r":{"a":1,"k":[{"i":{"x":[0.667],"y":[1]},"o":{"x":[0.333],"y":[0]},"t":0,"s":[0]},{"i":{"x":[0.667],"y":[1]},"o":{"x":[0.333],"y":[0]},"t":20,"s":[7]},{"i":{"x":[0.667],"y":[1]},"o":{"x":[0.333],"y":[0]},"t":45,"s":[0]},{"i":{"x":[0.667],"y":[1]},"o":{"x":[0.333],"y":[0]},"t":188,"s":[0]},{"i":{"x":[0.667],"y":[1]},"o":{"x":[0.333],"y":[0]},"t":215,"s":[-10]},{"i":{"x":[0.667],"y":[1]},"o":{"x":[0.333],"y":[0]},"t":281,"s":[17]},{"t":321,"s":[0]}],"ix":10},"p":{"a":0,"k":[1023.677,1166.818,0],"ix":2},"a":{"a":0,"k":[309.778,338.805,0],"ix":1},"s":{"a":0,"k":[100,100,100],"ix":6}},"ao":0,"hasMask":true,"masksProperties":[{"inv":false,"mode":"s","pt":{"a":1,"k":[{"i":{"x":0.833,"y":0.833},"o":{"x":0.167,"y":0.167},"t":55,"s":[{"i":[[60.808,4.012],[-39.133,3.671],[0,0]],"o":[[0,0],[39.133,-3.673],[0,0]],"v":[[240.208,198.019],[296.816,160.518],[342.947,162.707]],"c":true}]},{"i":{"x":0.833,"y":0.833},"o":{"x":0.167,"y":0.167},"t":104,"s":[{"i":[[73.893,-16.032],[-39.133,3.671],[0,0]],"o":[[0,0],[39.133,-3.673],[0,0]],"v":[[240.208,198.019],[296.816,160.518],[342.947,162.707]],"c":true}]},{"i":{"x":0.833,"y":0.833},"o":{"x":0.167,"y":0.167},"t":195,"s":[{"i":[[73.893,-16.032],[-39.133,3.671],[0,0]],"o":[[0,0],[39.133,-3.673],[0,0]],"v":[[240.208,198.019],[296.816,160.518],[342.947,162.707]],"c":true}]},{"t":244,"s":[{"i":[[60.808,4.012],[-39.133,3.671],[0,0]],"o":[[0,0],[39.133,-3.673],[0,0]],"v":[[240.208,198.019],[296.816,160.518],[342.947,162.707]],"c":true}]}],"ix":1},"o":{"a":0,"k":100,"ix":3},"x":{"a":0,"k":0,"ix":4},"nm":"Mask 1"},{"inv":false,"mode":"s","pt":{"a":1,"k":[{"i":{"x":0.833,"y":0.833},"o":{"x":0.167,"y":0.167},"t":55,"s":[{"i":[[0,0],[42.04,-1.819],[-18.227,-7.348]],"o":[[0,0],[-42.04,1.82],[11.866,4.784]],"v":[[120.214,215.035],[61.79,192.778],[63.396,213.87]],"c":true}]},{"i":{"x":0.833,"y":0.833},"o":{"x":0.167,"y":0.167},"t":104,"s":[{"i":[[0,0],[42.04,-1.819],[-18.227,-7.348]],"o":[[0,0],[-42.04,1.82],[11.866,4.784]],"v":[[120.214,215.035],[61.79,192.778],[65.396,208.87]],"c":true}]},{"i":{"x":0.833,"y":0.833},"o":{"x":0.167,"y":0.167},"t":195,"s":[{"i":[[0,0],[42.04,-1.819],[-18.227,-7.348]],"o":[[0,0],[-42.04,1.82],[11.866,4.784]],"v":[[120.214,215.035],[61.79,192.778],[65.396,208.87]],"c":true}]},{"t":244,"s":[{"i":[[0,0],[42.04,-1.819],[-18.227,-7.348]],"o":[[0,0],[-42.04,1.82],[11.866,4.784]],"v":[[120.214,215.035],[61.79,192.778],[63.396,213.87]],"c":true}]}],"ix":1},"o":{"a":0,"k":100,"ix":3},"x":{"a":0,"k":0,"ix":4},"nm":"Mask 2"}],"shapes":[{"ty":"gr","it":[{"ind":0,"ty":"sh","ix":1,"ks":{"a":0,"k":{"i":[[0,0],[-30,-17],[0,0],[-9,75]],"o":[[0,0],[30,17],[0,0],[9,-75]],"v":[[8.101,66.987],[-0.899,305.987],[77.101,303.987],[31.101,83.987]],"c":true},"ix":2},"nm":"Path 1","mn":"ADBE Vector Shape - Group","hd":false},{"ty":"st","c":{"a":0,"k":[0.992156982422,0.878431013519,0.796078969918,1],"ix":3},"o":{"a":0,"k":100,"ix":4},"w":{"a":0,"k":0,"ix":5},"lc":1,"lj":1,"ml":4,"bm":0,"nm":"Stroke 1","mn":"ADBE Vector Graphic - Stroke","hd":false},{"ty":"fl","c":{"a":0,"k":[0.792156922583,0.921568687289,0.945098099054,1],"ix":4},"o":{"a":0,"k":100,"ix":5},"r":1,"bm":0,"nm":"Fill 1","mn":"ADBE Vector Graphic - Fill","hd":false},{"ty":"tr","p":{"a":0,"k":[0,0],"ix":2},"a":{"a":0,"k":[0,0],"ix":1},"s":{"a":0,"k":[100,100],"ix":3},"r":{"a":0,"k":0,"ix":6},"o":{"a":0,"k":100,"ix":7},"sk":{"a":0,"k":0,"ix":4},"sa":{"a":0,"k":0,"ix":5},"nm":"Transform"}],"nm":"Shape 1","np":3,"cix":2,"bm":0,"ix":1,"mn":"ADBE Vector Group","hd":false},{"ty":"gr","it":[{"ind":0,"ty":"sh","ix":1,"ks":{"a":0,"k":{"i":[[-11.934,47.582],[15.334,1.598]],"o":[[0,0],[-15.334,-1.598]],"v":[[1.595,-23.817],[0,22.219]],"c":true},"ix":2},"nm":"Path 1","mn":"ADBE Vector Shape - Group","hd":false},{"ty":"fl","c":{"a":0,"k":[0.261918550379,0.078588964425,0.032551380232,1],"ix":4},"o":{"a":0,"k":100,"ix":5},"r":1,"bm":0,"nm":"Fill 1","mn":"ADBE Vector Graphic - Fill","hd":false},{"ty":"tr","p":{"a":0,"k":[176.955,273.216],"ix":2},"a":{"a":0,"k":[0,0],"ix":1},"s":{"a":0,"k":[100,100],"ix":3},"r":{"a":0,"k":0,"ix":6},"o":{"a":0,"k":100,"ix":7},"sk":{"a":0,"k":0,"ix":4},"sa":{"a":0,"k":0,"ix":5},"nm":"Transform"}],"nm":"Group 1","np":2,"cix":2,"bm":0,"ix":2,"mn":"ADBE Vector Group","hd":false},{"ty":"gr","it":[{"ind":0,"ty":"sh","ix":1,"ks":{"a":0,"k":{"i":[[-2.6,-11.737],[11.737,-2.599],[2.599,11.737],[-11.738,2.599]],"o":[[2.599,11.738],[-11.737,2.6],[-2.599,-11.738],[11.737,-2.6]],"v":[[21.253,-4.707],[4.706,21.253],[-21.253,4.707],[-4.706,-21.252]],"c":true},"ix":2},"nm":"Path 1","mn":"ADBE Vector Shape - Group","hd":false},{"ty":"fl","c":{"a":0,"k":[0.261918550379,0.078588964425,0.032551380232,1],"ix":4},"o":{"a":0,"k":100,"ix":5},"r":1,"bm":0,"nm":"Fill 1","mn":"ADBE Vector Graphic - Fill","hd":false},{"ty":"tr","p":{"a":0,"k":[284.851,234.837],"ix":2},"a":{"a":0,"k":[0,0],"ix":1},"s":{"a":0,"k":[100,100],"ix":3},"r":{"a":0,"k":0,"ix":6},"o":{"a":0,"k":100,"ix":7},"sk":{"a":0,"k":0,"ix":4},"sa":{"a":0,"k":0,"ix":5},"nm":"Transform"}],"nm":"Group 2","np":2,"cix":2,"bm":0,"ix":3,"mn":"ADBE Vector Group","hd":false},{"ty":"gr","it":[{"ind":0,"ty":"sh","ix":1,"ks":{"a":0,"k":{"i":[[-2.599,-11.737],[11.738,-2.6],[2.599,11.737],[-11.738,2.6]],"o":[[2.599,11.737],[-11.737,2.6],[-2.599,-11.737],[11.738,-2.599]],"v":[[21.253,-4.707],[4.706,21.253],[-21.253,4.706],[-4.706,-21.254]],"c":true},"ix":2},"nm":"Path 1","mn":"ADBE Vector Shape - Group","hd":false},{"ty":"fl","c":{"a":0,"k":[0.261918550379,0.078588964425,0.032551380232,1],"ix":4},"o":{"a":0,"k":100,"ix":5},"r":1,"bm":0,"nm":"Fill 1","mn":"ADBE Vector Graphic - Fill","hd":false},{"ty":"tr","p":{"a":0,"k":[90.525,255.384],"ix":2},"a":{"a":0,"k":[0,0],"ix":1},"s":{"a":0,"k":[100,100],"ix":3},"r":{"a":0,"k":0,"ix":6},"o":{"a":0,"k":100,"ix":7},"sk":{"a":0,"k":0,"ix":4},"sa":{"a":0,"k":0,"ix":5},"nm":"Transform"}],"nm":"Group 3","np":2,"cix":2,"bm":0,"ix":4,"mn":"ADBE Vector Group","hd":false},{"ty":"gr","it":[{"ind":0,"ty":"sh","ix":1,"ks":{"a":0,"k":{"i":[[-5.307,-23.967],[23.968,-5.306],[5.308,23.968],[-23.968,5.307]],"o":[[5.308,23.968],[-23.968,5.308],[-5.308,-23.968],[23.968,-5.307]],"v":[[43.397,-14.039],[-15.863,47.825],[-43.397,5.182],[-9.61,-47.826]],"c":true},"ix":2},"nm":"Path 1","mn":"ADBE Vector Shape - Group","hd":false},{"ty":"fl","c":{"a":0,"k":[0.614906400793,0.222524919697,0.055979235032,1],"ix":4},"o":{"a":0,"k":100,"ix":5},"r":1,"bm":0,"nm":"Fill 1","mn":"ADBE Vector Graphic - Fill","hd":false},{"ty":"tr","p":{"a":0,"k":[462.602,187.533],"ix":2},"a":{"a":0,"k":[0,0],"ix":1},"s":{"a":0,"k":[100,100],"ix":3},"r":{"a":0,"k":0,"ix":6},"o":{"a":0,"k":100,"ix":7},"sk":{"a":0,"k":0,"ix":4},"sa":{"a":0,"k":0,"ix":5},"nm":"Transform"}],"nm":"Group 4","np":2,"cix":2,"bm":0,"ix":5,"mn":"ADBE Vector Group","hd":false},{"ty":"gr","it":[{"ind":0,"ty":"sh","ix":1,"ks":{"a":0,"k":{"i":[[-32.963,-115.037],[-66.316,-62.711],[-31.467,4.471],[-28.355,86.171],[34.34,42.329],[130.353,-8.891]],"o":[[0,0],[66.317,62.711],[31.466,-4.471],[0,0],[-34.34,-42.329],[-130.354,8.892]],"v":[[-198.742,-52.4],[-115.341,143.844],[27.044,189.287],[213.206,56.771],[197.365,-112.649],[6.272,-197.664]],"c":true},"ix":2},"nm":"Path 1","mn":"ADBE Vector Shape - Group","hd":false},{"ty":"fl","c":{"a":0,"k":[0.614906400793,0.222524919697,0.055979235032,1],"ix":4},"o":{"a":0,"k":100,"ix":5},"r":1,"bm":0,"nm":"Fill 1","mn":"ADBE Vector Graphic - Fill","hd":false},{"ty":"tr","p":{"a":0,"k":[231.956,206.805],"ix":2},"a":{"a":0,"k":[0,0],"ix":1},"s":{"a":0,"k":[100,100],"ix":3},"r":{"a":0,"k":0,"ix":6},"o":{"a":0,"k":100,"ix":7},"sk":{"a":0,"k":0,"ix":4},"sa":{"a":0,"k":0,"ix":5},"nm":"Transform"}],"nm":"Group 5","np":2,"cix":2,"bm":0,"ix":6,"mn":"ADBE Vector Group","hd":false}],"ip":0,"op":514,"st":0,"bm":0},{"ddd":0,"ind":11,"ty":4,"nm":"pupil Outlines","parent":10,"sr":1,"ks":{"o":{"a":0,"k":100,"ix":11},"r":{"a":0,"k":0,"ix":10},"p":{"a":1,"k":[{"i":{"x":0.667,"y":1},"o":{"x":0.333,"y":0},"t":33,"s":[194.55,187.873,0],"to":[1.333,-2,0],"ti":[-1.333,2,0]},{"i":{"x":0.667,"y":0.667},"o":{"x":0.167,"y":0.167},"t":55,"s":[202.55,175.873,0],"to":[0,0,0],"ti":[0,0,0]},{"i":{"x":0.667,"y":1},"o":{"x":0.167,"y":0},"t":111,"s":[202.55,175.873,0],"to":[-7,2,0],"ti":[7,-2,0]},{"i":{"x":0.667,"y":0.667},"o":{"x":0.167,"y":0.167},"t":131,"s":[160.55,187.873,0],"to":[0,0,0],"ti":[0,0,0]},{"i":{"x":0.667,"y":1},"o":{"x":0.167,"y":0},"t":168,"s":[160.55,187.873,0],"to":[5.667,0,0],"ti":[-5.667,0,0]},{"i":{"x":0.667,"y":0.667},"o":{"x":0.167,"y":0.167},"t":180,"s":[194.55,187.873,0],"to":[0,0,0],"ti":[0,0,0]},{"i":{"x":0.667,"y":1},"o":{"x":0.167,"y":0},"t":225,"s":[194.55,187.873,0],"to":[-4,1.333,0],"ti":[4,-1.333,0]},{"i":{"x":0.667,"y":0.667},"o":{"x":0.167,"y":0.167},"t":232,"s":[170.55,195.873,0],"to":[0,0,0],"ti":[0,0,0]},{"i":{"x":0.667,"y":1},"o":{"x":0.167,"y":0},"t":242,"s":[170.55,195.873,0],"to":[4,-1.333,0],"ti":[-4,1.333,0]},{"t":280,"s":[194.55,187.873,0]}],"ix":2},"a":{"a":0,"k":[131.682,42.383,0],"ix":1},"s":{"a":0,"k":[100,100,100],"ix":6}},"ao":0,"shapes":[{"ty":"gr","it":[{"ind":0,"ty":"sh","ix":1,"ks":{"a":0,"k":{"i":[[0,-14.171],[14.171,0],[0,14.17],[-14.171,0]],"o":[[0,14.17],[-14.171,0],[0,-14.171],[14.171,0]],"v":[[25.658,0],[0,25.658],[-25.658,0],[0,-25.658]],"c":true},"ix":2},"nm":"Path 1","mn":"ADBE Vector Shape - Group","hd":false},{"ty":"fl","c":{"a":0,"k":[0,0,0,1],"ix":4},"o":{"a":0,"k":100,"ix":5},"r":1,"bm":0,"nm":"Fill 1","mn":"ADBE Vector Graphic - Fill","hd":false},{"ty":"tr","p":{"a":0,"k":[237.456,25.908],"ix":2},"a":{"a":0,"k":[0,0],"ix":1},"s":{"a":0,"k":[100,100],"ix":3},"r":{"a":0,"k":0,"ix":6},"o":{"a":0,"k":100,"ix":7},"sk":{"a":0,"k":0,"ix":4},"sa":{"a":0,"k":0,"ix":5},"nm":"Transform"}],"nm":"Group 1","np":2,"cix":2,"bm":0,"ix":1,"mn":"ADBE Vector Group","hd":false},{"ty":"gr","it":[{"ind":0,"ty":"sh","ix":1,"ks":{"a":0,"k":{"i":[[0,-13.612],[13.613,0],[0,13.613],[-13.613,0]],"o":[[0,13.613],[-13.613,0],[0,-13.612],[13.613,0]],"v":[[24.648,-0.001],[0,24.647],[-24.648,-0.001],[0,-24.647]],"c":true},"ix":2},"nm":"Path 1","mn":"ADBE Vector Shape - Group","hd":false},{"ty":"fl","c":{"a":0,"k":[0,0,0,1],"ix":4},"o":{"a":0,"k":100,"ix":5},"r":1,"bm":0,"nm":"Fill 1","mn":"ADBE Vector Graphic - Fill","hd":false},{"ty":"tr","p":{"a":0,"k":[24.898,59.868],"ix":2},"a":{"a":0,"k":[0,0],"ix":1},"s":{"a":0,"k":[100,100],"ix":3},"r":{"a":0,"k":0,"ix":6},"o":{"a":0,"k":100,"ix":7},"sk":{"a":0,"k":0,"ix":4},"sa":{"a":0,"k":0,"ix":5},"nm":"Transform"}],"nm":"Group 2","np":2,"cix":2,"bm":0,"ix":2,"mn":"ADBE Vector Group","hd":false}],"ip":0,"op":514,"st":0,"bm":0},{"ddd":0,"ind":12,"ty":4,"nm":"Shape Layer 1","parent":10,"sr":1,"ks":{"o":{"a":0,"k":100,"ix":11},"r":{"a":0,"k":-4.536,"ix":10},"p":{"a":0,"k":[272.983,174.382,0],"ix":2},"a":{"a":0,"k":[0,0,0],"ix":1},"s":{"a":0,"k":[100,100,100],"ix":6}},"ao":0,"shapes":[{"ty":"gr","it":[{"ind":0,"ty":"sh","ix":1,"ks":{"a":0,"k":{"i":[[0,0],[0,0],[0,0],[0,0]],"o":[[0,0],[0,0],[0,0],[0,0]],"v":[[221.648,-135.648],[-162.648,-76.648],[-145.648,-4.352],[191.648,65.648]],"c":true},"ix":2},"nm":"Path 1","mn":"ADBE Vector Shape - Group","hd":false},{"ty":"st","c":{"a":0,"k":[0.992156982422,0.878431013519,0.796078969918,1],"ix":3},"o":{"a":0,"k":100,"ix":4},"w":{"a":0,"k":0,"ix":5},"lc":1,"lj":1,"ml":4,"bm":0,"nm":"Stroke 1","mn":"ADBE Vector Graphic - Stroke","hd":false},{"ty":"fl","c":{"a":0,"k":[1,1,1,1],"ix":4},"o":{"a":0,"k":100,"ix":5},"r":1,"bm":0,"nm":"Fill 1","mn":"ADBE Vector Graphic - Fill","hd":false},{"ty":"tr","p":{"a":0,"k":[-71.352,75.648],"ix":2},"a":{"a":0,"k":[0,0],"ix":1},"s":{"a":0,"k":[100,100],"ix":3},"r":{"a":0,"k":0,"ix":6},"o":{"a":0,"k":100,"ix":7},"sk":{"a":0,"k":0,"ix":4},"sa":{"a":0,"k":0,"ix":5},"nm":"Transform"}],"nm":"Rectangle 1","np":3,"cix":2,"bm":0,"ix":1,"mn":"ADBE Vector Group","hd":false}],"ip":0,"op":514,"st":0,"bm":0},{"ddd":0,"ind":13,"ty":4,"nm":"collo Outlines","sr":1,"ks":{"o":{"a":0,"k":100,"ix":11},"r":{"a":0,"k":0,"ix":10},"p":{"a":0,"k":[990.305,1263.242,0],"ix":2},"a":{"a":0,"k":[104.959,191.511,0],"ix":1},"s":{"a":0,"k":[100,100,100],"ix":6}},"ao":0,"shapes":[{"ty":"gr","it":[{"ind":0,"ty":"sh","ix":1,"ks":{"a":0,"k":{"i":[[0,0],[-49.35,82.251],[0,0],[0,0]],"o":[[0,0],[49.351,-82.251],[0,0],[0,0]],"v":[[75.241,191.261],[-55.359,70.522],[-4.601,-148.545],[104.709,-191.261]],"c":true},"ix":2},"nm":"Path 1","mn":"ADBE Vector Shape - Group","hd":false},{"ty":"fl","c":{"a":0,"k":[0.614906400793,0.222524919697,0.055979235032,1],"ix":4},"o":{"a":0,"k":100,"ix":5},"r":1,"bm":0,"nm":"Fill 1","mn":"ADBE Vector Graphic - Fill","hd":false},{"ty":"tr","p":{"a":0,"k":[104.959,191.511],"ix":2},"a":{"a":0,"k":[0,0],"ix":1},"s":{"a":0,"k":[100,100],"ix":3},"r":{"a":0,"k":0,"ix":6},"o":{"a":0,"k":100,"ix":7},"sk":{"a":0,"k":0,"ix":4},"sa":{"a":0,"k":0,"ix":5},"nm":"Transform"}],"nm":"Group 1","np":2,"cix":2,"bm":0,"ix":1,"mn":"ADBE Vector Group","hd":false}],"ip":0,"op":514,"st":0,"bm":0},{"ddd":0,"ind":14,"ty":4,"nm":"capelli Outlines","parent":10,"sr":1,"ks":{"o":{"a":0,"k":100,"ix":11},"r":{"a":1,"k":[{"i":{"x":[0.667],"y":[1]},"o":{"x":[0.333],"y":[0]},"t":5,"s":[0]},{"i":{"x":[0.833],"y":[1]},"o":{"x":[0.333],"y":[0]},"t":23,"s":[-7]},{"i":{"x":[0.667],"y":[1]},"o":{"x":[0.333],"y":[0]},"t":51,"s":[0]},{"i":{"x":[0.667],"y":[1]},"o":{"x":[0.333],"y":[0]},"t":188,"s":[0]},{"i":{"x":[0.667],"y":[1]},"o":{"x":[0.333],"y":[0]},"t":215,"s":[3]},{"i":{"x":[0.667],"y":[1]},"o":{"x":[0.333],"y":[0]},"t":289,"s":[-10]},{"t":329,"s":[0]}],"ix":10},"p":{"a":0,"k":[263.075,106.973,0],"ix":2},"a":{"a":0,"k":[440.604,302.671,0],"ix":1},"s":{"a":0,"k":[100,100,100],"ix":6}},"ao":0,"shapes":[{"ty":"gr","it":[{"ind":0,"ty":"sh","ix":1,"ks":{"a":0,"k":{"i":[[0,0],[-132.944,-171.821]],"o":[[-125.21,117.132],[0,0]],"v":[[133.46,-239.04],[-0.516,239.041]],"c":false},"ix":2},"nm":"Path 1","mn":"ADBE Vector Shape - Group","hd":false},{"ty":"st","c":{"a":0,"k":[0.793050309723,0.922270711263,0.946181832108,1],"ix":3},"o":{"a":0,"k":100,"ix":4},"w":{"a":0,"k":7.01,"ix":5},"lc":1,"lj":1,"ml":10,"bm":0,"nm":"Stroke 1","mn":"ADBE Vector Graphic - Stroke","hd":false},{"ty":"tr","p":{"a":0,"k":[150.985,313.294],"ix":2},"a":{"a":0,"k":[0,0],"ix":1},"s":{"a":0,"k":[100,100],"ix":3},"r":{"a":0,"k":0,"ix":6},"o":{"a":0,"k":100,"ix":7},"sk":{"a":0,"k":0,"ix":4},"sa":{"a":0,"k":0,"ix":5},"nm":"Transform"}],"nm":"Group 1","np":2,"cix":2,"bm":0,"ix":1,"mn":"ADBE Vector Group","hd":false},{"ty":"gr","it":[{"ind":0,"ty":"sh","ix":1,"ks":{"a":0,"k":{"i":[[0,0],[17.49,-131.985],[6.522,-21.335],[8.763,-20.154],[-6.14,-16.047]],"o":[[139.626,47.417],[-3.738,21.917],[-6.522,21.323],[0,14.02],[0,0]],"v":[[-94.348,-259.559],[76.858,81.075],[61.33,146.064],[38.268,208.462],[51.418,259.559]],"c":false},"ix":2},"nm":"Path 1","mn":"ADBE Vector Shape - Group","hd":false},{"ty":"st","c":{"a":0,"k":[0.793050309723,0.922270711263,0.946181832108,1],"ix":3},"o":{"a":0,"k":100,"ix":4},"w":{"a":0,"k":7.01,"ix":5},"lc":1,"lj":1,"ml":10,"bm":0,"nm":"Stroke 1","mn":"ADBE Vector Graphic - Stroke","hd":false},{"ty":"tr","p":{"a":0,"k":[750.363,305.243],"ix":2},"a":{"a":0,"k":[0,0],"ix":1},"s":{"a":0,"k":[100,100],"ix":3},"r":{"a":0,"k":0,"ix":6},"o":{"a":0,"k":100,"ix":7},"sk":{"a":0,"k":0,"ix":4},"sa":{"a":0,"k":0,"ix":5},"nm":"Transform"}],"nm":"Group 2","np":2,"cix":2,"bm":0,"ix":2,"mn":"ADBE Vector Group","hd":false},{"ty":"gr","it":[{"ind":0,"ty":"sh","ix":1,"ks":{"a":0,"k":{"i":[[0,0],[-27.82,-26.738],[-11.446,-15.03],[7.01,-56.08],[-30.992,-72.82]],"o":[[35.138,22.19],[13.909,13.369],[35.332,49.217],[0,70.1],[0,0]],"v":[[-94.767,-244.947],[0.184,-171.878],[38.406,-129.452],[87.757,38.936],[69.679,244.947]],"c":false},"ix":2},"nm":"Path 1","mn":"ADBE Vector Shape - Group","hd":false},{"ty":"st","c":{"a":0,"k":[0.793050309723,0.922270711263,0.946181832108,1],"ix":3},"o":{"a":0,"k":100,"ix":4},"w":{"a":0,"k":7.01,"ix":5},"lc":1,"lj":1,"ml":10,"bm":0,"nm":"Stroke 1","mn":"ADBE Vector Graphic - Stroke","hd":false},{"ty":"tr","p":{"a":0,"k":[768.916,331.287],"ix":2},"a":{"a":0,"k":[0,0],"ix":1},"s":{"a":0,"k":[100,100],"ix":3},"r":{"a":0,"k":0,"ix":6},"o":{"a":0,"k":100,"ix":7},"sk":{"a":0,"k":0,"ix":4},"sa":{"a":0,"k":0,"ix":5},"nm":"Transform"}],"nm":"Group 3","np":2,"cix":2,"bm":0,"ix":3,"mn":"ADBE Vector Group","hd":false},{"ty":"gr","it":[{"ind":0,"ty":"sh","ix":1,"ks":{"a":0,"k":{"i":[[0,0],[-42.377,8.948],[-20.94,0.434],[-63.178,-1.077],[-11.273,35.53],[0.683,18.631],[5.175,19.135],[5.054,17.759],[49.191,43.436],[14.684,16.973],[67.861,5.675],[23.271,-1.441],[20.298,-2.239],[40.44,-91.712],[8.698,-22.814],[-117.011,-36.004],[-83.685,2.487]],"o":[[41.492,-2.723],[20.867,-0.533],[62.822,-1.304],[-1.347,-35.025],[1.278,-18.474],[-0.692,-18.632],[-2.775,-18.376],[-15.185,-53.254],[-14.29,-18.28],[-40.414,-47.551],[-22.622,-1.892],[-19.633,2.743],[-44.654,8.223],[-10.11,22.928],[-52.237,101.291],[23.325,7.177],[13.646,-0.283]],"v":[[6.693,254.784],[133.131,255.505],[195.846,254.034],[353.757,259.299],[386.261,140.817],[387.779,85.245],[379.614,28.682],[368.013,-25.576],[276.946,-172.259],[233.266,-225.083],[62.755,-300.468],[-6.383,-300.98],[-66.742,-294.169],[-279.6,-127.268],[-307.482,-58.021],[-271.451,295.244],[-34.619,266.537]],"c":true},"ix":2},"nm":"Path 1","mn":"ADBE Vector Shape - Group","hd":false},{"ty":"fl","c":{"a":0,"k":[0.793050309723,0.922270711263,0.946181832108,1],"ix":4},"o":{"a":0,"k":100,"ix":5},"r":1,"bm":0,"nm":"Fill 1","mn":"ADBE Vector Graphic - Fill","hd":false},{"ty":"tr","p":{"a":0,"k":[463.321,302.671],"ix":2},"a":{"a":0,"k":[0,0],"ix":1},"s":{"a":0,"k":[100,100],"ix":3},"r":{"a":0,"k":0,"ix":6},"o":{"a":0,"k":100,"ix":7},"sk":{"a":0,"k":0,"ix":4},"sa":{"a":0,"k":0,"ix":5},"nm":"Transform"}],"nm":"Group 4","np":2,"cix":2,"bm":0,"ix":4,"mn":"ADBE Vector Group","hd":false}],"ip":-39,"op":522,"st":8,"bm":0},{"ddd":0,"ind":15,"ty":4,"nm":"hand lx Outlines","sr":1,"ks":{"o":{"a":0,"k":100,"ix":11},"r":{"a":1,"k":[{"i":{"x":[0.667],"y":[0.805]},"o":{"x":[0.333],"y":[0]},"t":1,"s":[67]},{"i":{"x":[0.667],"y":[1]},"o":{"x":[0.333],"y":[-0.813]},"t":9,"s":[-17.749]},{"i":{"x":[0.612],"y":[1]},"o":{"x":[0.276],"y":[0]},"t":16,"s":[0]},{"i":{"x":[0.667],"y":[1]},"o":{"x":[0.227],"y":[0]},"t":51,"s":[25]},{"i":{"x":[0.612],"y":[1]},"o":{"x":[0.276],"y":[0]},"t":94,"s":[0]},{"i":{"x":[0.667],"y":[1]},"o":{"x":[0.227],"y":[0]},"t":129,"s":[25]},{"i":{"x":[0.612],"y":[1]},"o":{"x":[0.276],"y":[0]},"t":174,"s":[0]},{"i":{"x":[0.667],"y":[1]},"o":{"x":[0.227],"y":[0]},"t":209,"s":[25]},{"i":{"x":[0.612],"y":[1]},"o":{"x":[0.276],"y":[0]},"t":246,"s":[0]},{"i":{"x":[0.838],"y":[1]},"o":{"x":[0.227],"y":[0]},"t":281,"s":[25]},{"i":{"x":[0.833],"y":[1]},"o":{"x":[0.167],"y":[0]},"t":310,"s":[0]},{"t":332,"s":[67]}],"ix":10},"p":{"a":0,"k":[411.645,1408.909,0],"ix":2},"a":{"a":0,"k":[88.127,44.363,0],"ix":1},"s":{"a":0,"k":[100,100,100],"ix":6}},"ao":0,"shapes":[{"ty":"gr","it":[{"ind":0,"ty":"sh","ix":1,"ks":{"a":0,"k":{"i":[[0.099,0.903],[-6.46,-1.093],[0,0],[-5.227,1.677],[-4.776,-2.874],[-5.238,-0.827],[0,0],[-7.717,-6.309],[38.951,-1.853],[0,0]],"o":[[-2.709,-6.279],[-12.826,-17.993],[0,0],[5.747,-1.844],[4.961,2.984],[10.018,1.58],[0,0],[14.766,12.071],[-18.028,0.858],[0,0]],"v":[[-51.167,-5.481],[-33.086,-4.733],[-32.051,-19.04],[-27.772,-23.668],[-5.965,-12.689],[-10.534,-27.286],[7.979,-9.256],[39.111,-3.144],[14.208,27.255],[-16.65,22.017]],"c":true},"ix":2},"nm":"Path 1","mn":"ADBE Vector Shape - Group","hd":false},{"ty":"fl","c":{"a":0,"k":[0.614906400793,0.222524919697,0.055979235032,1],"ix":4},"o":{"a":0,"k":100,"ix":5},"r":1,"bm":0,"nm":"Fill 1","mn":"ADBE Vector Graphic - Fill","hd":false},{"ty":"tr","p":{"a":0,"k":[54.126,28.363],"ix":2},"a":{"a":0,"k":[0,0],"ix":1},"s":{"a":0,"k":[100,100],"ix":3},"r":{"a":0,"k":0,"ix":6},"o":{"a":0,"k":100,"ix":7},"sk":{"a":0,"k":0,"ix":4},"sa":{"a":0,"k":0,"ix":5},"nm":"Transform"}],"nm":"Group 1","np":2,"cix":2,"bm":0,"ix":1,"mn":"ADBE Vector Group","hd":false}],"ip":0,"op":514,"st":0,"bm":0},{"ddd":0,"ind":16,"ty":4,"nm":"hand rx Outlines","sr":1,"ks":{"o":{"a":0,"k":100,"ix":11},"r":{"a":1,"k":[{"i":{"x":[0.667],"y":[1]},"o":{"x":[0.333],"y":[0]},"t":0,"s":[0]},{"i":{"x":[0.667],"y":[1]},"o":{"x":[0.333],"y":[0]},"t":16,"s":[25]},{"t":38,"s":[0]}],"ix":10,"x":"var $bm_rt;\n$bm_rt = loopOut();"},"p":{"a":0,"k":[1085.473,1495.417,0],"ix":2},"a":{"a":0,"k":[89.855,23.237,0],"ix":1},"s":{"a":0,"k":[100,100,100],"ix":6}},"ao":0,"shapes":[{"ty":"gr","it":[{"ind":0,"ty":"sh","ix":1,"ks":{"a":0,"k":{"i":[[0.225,-0.88],[-6.548,0.17],[0,0],[-4.937,-2.399],[-5.135,2.169],[-5.302,0.079],[0,0],[-8.532,5.156],[38.299,7.335],[0,0]],"o":[[-3.569,5.834],[-15.236,16.001],[0,0],[5.429,2.636],[5.331,-2.254],[10.142,-0.15],[0,0],[16.322,-9.866],[-17.725,-3.394],[0,0]],"v":[[-52.036,-0.416],[-34.032,1.397],[-35.027,15.707],[-31.444,20.893],[-8.303,13.104],[-14.888,26.908],[5.984,11.674],[37.668,10.019],[17.306,-23.593],[-13.983,-22.765]],"c":true},"ix":2},"nm":"Path 1","mn":"ADBE Vector Shape - Group","hd":false},{"ty":"fl","c":{"a":0,"k":[0.614906400793,0.222524919697,0.055979235032,1],"ix":4},"o":{"a":0,"k":100,"ix":5},"r":1,"bm":0,"nm":"Fill 1","mn":"ADBE Vector Graphic - Fill","hd":false},{"ty":"tr","p":{"a":0,"k":[55.855,27.237],"ix":2},"a":{"a":0,"k":[0,0],"ix":1},"s":{"a":0,"k":[100,100],"ix":3},"r":{"a":0,"k":0,"ix":6},"o":{"a":0,"k":100,"ix":7},"sk":{"a":0,"k":0,"ix":4},"sa":{"a":0,"k":0,"ix":5},"nm":"Transform"}],"nm":"Group 1","np":2,"cix":2,"bm":0,"ix":1,"mn":"ADBE Vector Group","hd":false}],"ip":-37,"op":477,"st":-37,"bm":0},{"ddd":0,"ind":17,"ty":4,"nm":"forearmrx Outlines","sr":1,"ks":{"o":{"a":0,"k":100,"ix":11},"r":{"a":0,"k":0,"ix":10},"p":{"a":0,"k":[1238.914,1665.605,0],"ix":2},"a":{"a":0,"k":[157.135,181.743,0],"ix":1},"s":{"a":0,"k":[100,100,100],"ix":6}},"ao":0,"shapes":[{"ty":"gr","it":[{"ind":0,"ty":"sh","ix":1,"ks":{"a":0,"k":{"i":[[15.522,-5.174],[-85.827,-71.522],[-41.307,26.087],[79.287,61.624]],"o":[[23.566,46.839],[26.089,21.74],[14.193,-8.964],[-79.286,-61.624]],"v":[[-156.885,-176.319],[5.855,124.969],[131.95,155.406],[77.598,-42.432]],"c":true},"ix":2},"nm":"Path 1","mn":"ADBE Vector Shape - Group","hd":false},{"ty":"fl","c":{"a":0,"k":[0.614906400793,0.222524919697,0.055979235032,1],"ix":4},"o":{"a":0,"k":100,"ix":5},"r":1,"bm":0,"nm":"Fill 1","mn":"ADBE Vector Graphic - Fill","hd":false},{"ty":"tr","p":{"a":0,"k":[157.135,181.743],"ix":2},"a":{"a":0,"k":[0,0],"ix":1},"s":{"a":0,"k":[100,100],"ix":3},"r":{"a":0,"k":0,"ix":6},"o":{"a":0,"k":100,"ix":7},"sk":{"a":0,"k":0,"ix":4},"sa":{"a":0,"k":0,"ix":5},"nm":"Transform"}],"nm":"Group 1","np":2,"cix":2,"bm":0,"ix":1,"mn":"ADBE Vector Group","hd":false}],"ip":0,"op":514,"st":0,"bm":0},{"ddd":0,"ind":18,"ty":4,"nm":"arm lx Outlines","sr":1,"ks":{"o":{"a":0,"k":100,"ix":11},"r":{"a":0,"k":0,"ix":10},"p":{"a":0,"k":[664.364,1577.883,0],"ix":2},"a":{"a":0,"k":[262.92,250.993,0],"ix":1},"s":{"a":0,"k":[100,100,100],"ix":6}},"ao":0,"shapes":[{"ty":"gr","it":[{"ind":0,"ty":"sh","ix":1,"ks":{"a":0,"k":{"i":[[0,0],[-5.443,-2.991],[0,0],[2.553,-14.181]],"o":[[0,0],[14.949,8.213],[0,0],[-6.142,9.449]],"v":[[-17.947,-1.113],[9.41,-16.091],[25.947,-1.185],[-7.344,25.432]],"c":true},"ix":2},"nm":"Path 1","mn":"ADBE Vector Shape - Group","hd":false},{"ty":"fl","c":{"a":0,"k":[0.082259009866,0.062031566395,0.066909408569,1],"ix":4},"o":{"a":0,"k":100,"ix":5},"r":1,"bm":0,"nm":"Fill 1","mn":"ADBE Vector Graphic - Fill","hd":false},{"ty":"tr","p":{"a":0,"k":[26.589,107.191],"ix":2},"a":{"a":0,"k":[0,0],"ix":1},"s":{"a":0,"k":[100,100],"ix":3},"r":{"a":0,"k":0,"ix":6},"o":{"a":0,"k":100,"ix":7},"sk":{"a":0,"k":0,"ix":4},"sa":{"a":0,"k":0,"ix":5},"nm":"Transform"}],"nm":"Group 1","np":2,"cix":2,"bm":0,"ix":1,"mn":"ADBE Vector Group","hd":false},{"ty":"gr","it":[{"ind":0,"ty":"sh","ix":1,"ks":{"a":0,"k":{"i":[[-235.071,-98.866],[-25.39,108.798],[50.827,-45.031],[0,0],[0,0]],"o":[[50.667,21.31],[24.888,-106.648],[-66.595,59.003],[2.748,8.677],[0,0]],"v":[[15.45,229.433],[237.782,-114.29],[161.555,-205.712],[-5.956,9.252],[-262.67,-187.423]],"c":true},"ix":2},"nm":"Path 1","mn":"ADBE Vector Shape - Group","hd":false},{"ty":"fl","c":{"a":0,"k":[0.614906400793,0.222524919697,0.055979235032,1],"ix":4},"o":{"a":0,"k":100,"ix":5},"r":1,"bm":0,"nm":"Fill 1","mn":"ADBE Vector Graphic - Fill","hd":false},{"ty":"tr","p":{"a":0,"k":[262.92,250.993],"ix":2},"a":{"a":0,"k":[0,0],"ix":1},"s":{"a":0,"k":[100,100],"ix":3},"r":{"a":0,"k":0,"ix":6},"o":{"a":0,"k":100,"ix":7},"sk":{"a":0,"k":0,"ix":4},"sa":{"a":0,"k":0,"ix":5},"nm":"Transform"}],"nm":"Group 2","np":2,"cix":2,"bm":0,"ix":2,"mn":"ADBE Vector Group","hd":false}],"ip":0,"op":514,"st":0,"bm":0},{"ddd":0,"ind":19,"ty":4,"nm":"Layer 16 Outlines","sr":1,"ks":{"o":{"a":0,"k":100,"ix":11},"r":{"a":0,"k":0,"ix":10},"p":{"a":0,"k":[1011.439,1593.185,0],"ix":2},"a":{"a":0,"k":[223.822,278.022,0],"ix":1},"s":{"a":0,"k":[100,100,100],"ix":6}},"ao":0,"shapes":[{"ty":"gr","it":[{"ind":0,"ty":"sh","ix":1,"ks":{"a":0,"k":{"i":[[26.751,-11.313],[5.24,-11.726],[16.194,-6.847],[-10.86,-25.682],[-5.152,10.617],[11.312,26.751]],"o":[[-12.764,5.397],[-13.637,-9.035],[-25.682,10.861],[10.86,25.681],[14.393,10.302],[-11.313,-26.752]],"v":[[16.215,-72.513],[-11.182,-45.48],[-58.75,-49.949],[-85.588,16.216],[14.579,73.209],[85.136,-44.557]],"c":true},"ix":2},"nm":"Path 1","mn":"ADBE Vector Shape - Group","hd":false},{"ty":"fl","c":{"a":0,"k":[0.793050309723,0.922270711263,0.946181832108,1],"ix":4},"o":{"a":0,"k":100,"ix":5},"r":1,"bm":0,"nm":"Fill 1","mn":"ADBE Vector Graphic - Fill","hd":false},{"ty":"tr","p":{"a":0,"k":[218.264,273.881],"ix":2},"a":{"a":0,"k":[0,0],"ix":1},"s":{"a":0,"k":[100,100],"ix":3},"r":{"a":0,"k":0,"ix":6},"o":{"a":0,"k":100,"ix":7},"sk":{"a":0,"k":0,"ix":4},"sa":{"a":0,"k":0,"ix":5},"nm":"Transform"}],"nm":"Group 1","np":2,"cix":2,"bm":0,"ix":1,"mn":"ADBE Vector Group","hd":false},{"ty":"gr","it":[{"ind":0,"ty":"sh","ix":1,"ks":{"a":0,"k":{"i":[[0,0],[-16.621,204.203],[0,0],[-46.227,-36.926],[-6.213,-34.796],[47.691,-23.235]],"o":[[-40.3,-16.486],[5.489,-67.431],[119.716,-57.949],[28.059,22.415],[16.45,92.12],[-102.299,49.838]],"v":[[-122.272,126.46],[-185.647,-69.844],[-135.783,-214.685],[85.22,-240.846],[184.576,-63.388],[132.881,132.934]],"c":true},"ix":2},"nm":"Path 1","mn":"ADBE Vector Shape - Group","hd":false},{"ty":"fl","c":{"a":0,"k":[0.999999940162,0.999999940162,1,1],"ix":4},"o":{"a":0,"k":100,"ix":5},"r":1,"bm":0,"nm":"Fill 1","mn":"ADBE Vector Graphic - Fill","hd":false},{"ty":"tr","p":{"a":0,"k":[223.822,278.022],"ix":2},"a":{"a":0,"k":[0,0],"ix":1},"s":{"a":0,"k":[100,100],"ix":3},"r":{"a":0,"k":0,"ix":6},"o":{"a":0,"k":100,"ix":7},"sk":{"a":0,"k":0,"ix":4},"sa":{"a":0,"k":0,"ix":5},"nm":"Transform"}],"nm":"Group 2","np":2,"cix":2,"bm":0,"ix":2,"mn":"ADBE Vector Group","hd":false}],"ip":0,"op":514,"st":0,"bm":0},{"ddd":0,"ind":20,"ty":4,"nm":"arm rx Outlines","sr":1,"ks":{"o":{"a":0,"k":100,"ix":11},"r":{"a":0,"k":0,"ix":10},"p":{"a":0,"k":[1211.612,1565.32,0],"ix":2},"a":{"a":0,"k":[191.501,240.499,0],"ix":1},"s":{"a":0,"k":[100,100,100],"ix":6}},"ao":0,"shapes":[{"ty":"gr","it":[{"ind":0,"ty":"sh","ix":1,"ks":{"a":0,"k":{"i":[[-85.371,2.587],[54.791,97.363],[17.521,-65.606],[-24.293,-56.545]],"o":[[54.94,-1.665],[-53.708,-95.44],[-36.174,135.451],[24.293,56.545]],"v":[[136.311,237.661],[-7.618,-122.901],[-155.077,-174.642],[-72.297,106.079]],"c":true},"ix":2},"nm":"Path 1","mn":"ADBE Vector Shape - Group","hd":false},{"ty":"fl","c":{"a":0,"k":[0.614906400793,0.222524919697,0.055979235032,1],"ix":4},"o":{"a":0,"k":100,"ix":5},"r":1,"bm":0,"nm":"Fill 1","mn":"ADBE Vector Graphic - Fill","hd":false},{"ty":"tr","p":{"a":0,"k":[191.5,240.499],"ix":2},"a":{"a":0,"k":[0,0],"ix":1},"s":{"a":0,"k":[100,100],"ix":3},"r":{"a":0,"k":0,"ix":6},"o":{"a":0,"k":100,"ix":7},"sk":{"a":0,"k":0,"ix":4},"sa":{"a":0,"k":0,"ix":5},"nm":"Transform"}],"nm":"Group 1","np":2,"cix":2,"bm":0,"ix":1,"mn":"ADBE Vector Group","hd":false}],"ip":0,"op":514,"st":0,"bm":0},{"ddd":0,"ind":21,"ty":4,"nm":"Layer 1 Outlines","sr":1,"ks":{"o":{"a":0,"k":100,"ix":11},"r":{"a":0,"k":0,"ix":10},"p":{"a":0,"k":[1033.776,1119.518,0],"ix":2},"a":{"a":0,"k":[629.125,629.125,0],"ix":1},"s":{"a":0,"k":[100,100,100],"ix":6}},"ao":0,"shapes":[{"ty":"gr","it":[{"ind":0,"ty":"sh","ix":1,"ks":{"a":0,"k":{"i":[[-14.216,-339.467],[339.468,-14.215],[14.215,339.467],[-339.467,14.215]],"o":[[14.215,339.467],[-339.466,14.215],[-14.215,-339.467],[339.466,-14.216]],"v":[[614.659,-25.739],[25.739,614.659],[-614.659,25.74],[-25.738,-614.658]],"c":true},"ix":2},"nm":"Path 1","mn":"ADBE Vector Shape - Group","hd":false},{"ty":"fl","c":{"a":0,"k":[0.695726102941,0.565145155963,0.510156489354,1],"ix":4},"o":{"a":0,"k":100,"ix":5},"r":1,"bm":0,"nm":"Fill 1","mn":"ADBE Vector Graphic - Fill","hd":false},{"ty":"tr","p":{"a":0,"k":[629.125,629.125],"ix":2},"a":{"a":0,"k":[0,0],"ix":1},"s":{"a":0,"k":[100,100],"ix":3},"r":{"a":0,"k":0,"ix":6},"o":{"a":0,"k":100,"ix":7},"sk":{"a":0,"k":0,"ix":4},"sa":{"a":0,"k":0,"ix":5},"nm":"Transform"}],"nm":"Group 1","np":2,"cix":2,"bm":0,"ix":1,"mn":"ADBE Vector Group","hd":false}],"ip":0,"op":514,"st":0,"bm":0},{"ddd":0,"ind":22,"ty":4,"nm":"heart2","sr":1,"ks":{"o":{"a":1,"k":[{"i":{"x":[0.833],"y":[0.833]},"o":{"x":[0.167],"y":[0.167]},"t":0,"s":[0]},{"i":{"x":[0.833],"y":[0.833]},"o":{"x":[0.167],"y":[0.167]},"t":22,"s":[100]},{"i":{"x":[0.833],"y":[0.833]},"o":{"x":[0.167],"y":[0.167]},"t":300,"s":[100]},{"t":334,"s":[0]}],"ix":11},"r":{"a":0,"k":13,"ix":10},"p":{"a":1,"k":[{"i":{"x":0.667,"y":1},"o":{"x":0.333,"y":0},"t":0,"s":[395.439,1321.185,0],"to":[0,-1.667,0],"ti":[0,0,0]},{"i":{"x":0.667,"y":1},"o":{"x":0.333,"y":0},"t":13,"s":[395.439,1311.185,0],"to":[0,0,0],"ti":[0,-1.667,0]},{"t":24,"s":[395.439,1321.185,0]}],"ix":2,"x":"var $bm_rt;\n$bm_rt = loopOut('cycle', 0);"},"a":{"a":0,"k":[223.822,278.022,0],"ix":1},"s":{"a":0,"k":[51,51,100],"ix":6}},"ao":0,"shapes":[{"ty":"gr","it":[{"ind":0,"ty":"sh","ix":1,"ks":{"a":0,"k":{"i":[[26.751,-11.313],[5.24,-11.726],[16.194,-6.847],[-10.86,-25.682],[-5.152,10.617],[11.312,26.751]],"o":[[-12.764,5.397],[-13.637,-9.035],[-25.682,10.861],[10.86,25.681],[14.393,10.302],[-11.313,-26.752]],"v":[[16.215,-72.513],[-11.182,-45.48],[-58.75,-49.949],[-85.588,16.216],[14.579,73.209],[85.136,-44.557]],"c":true},"ix":2},"nm":"Path 1","mn":"ADBE Vector Shape - Group","hd":false},{"ty":"fl","c":{"a":0,"k":[0.793050309723,0.922270711263,0.946181832108,1],"ix":4},"o":{"a":0,"k":100,"ix":5},"r":1,"bm":0,"nm":"Fill 1","mn":"ADBE Vector Graphic - Fill","hd":false},{"ty":"tr","p":{"a":0,"k":[218.264,273.881],"ix":2},"a":{"a":0,"k":[0,0],"ix":1},"s":{"a":0,"k":[100,100],"ix":3},"r":{"a":0,"k":0,"ix":6},"o":{"a":0,"k":100,"ix":7},"sk":{"a":0,"k":0,"ix":4},"sa":{"a":0,"k":0,"ix":5},"nm":"Transform"}],"nm":"Group 1","np":2,"cix":2,"bm":0,"ix":1,"mn":"ADBE Vector Group","hd":false},{"ty":"gr","it":[{"ty":"fl","c":{"a":0,"k":[0.999999940162,0.999999940162,1,1],"ix":4},"o":{"a":0,"k":100,"ix":5},"r":1,"bm":0,"nm":"Fill 1","mn":"ADBE Vector Graphic - Fill","hd":false},{"ty":"tr","p":{"a":0,"k":[223.822,278.022],"ix":2},"a":{"a":0,"k":[0,0],"ix":1},"s":{"a":0,"k":[100,100],"ix":3},"r":{"a":0,"k":0,"ix":6},"o":{"a":0,"k":100,"ix":7},"sk":{"a":0,"k":0,"ix":4},"sa":{"a":0,"k":0,"ix":5},"nm":"Transform"}],"nm":"Group 2","np":1,"cix":2,"bm":0,"ix":2,"mn":"ADBE Vector Group","hd":false}],"ip":0,"op":514,"st":0,"bm":0}],"markers":[]}